{
  "dataJson": {
    "responseMessage": {},
    "responseData": {
      "score_list": [
        {
          "maxRecommendTime": "1508745194933",
          "minRecommendTime": "1508736708875"
        }
      ],
      "data_list": [
        {
          "isFollow": 0,
          "resourceNum": "",
          "picUrl": "https:\/\/img00.allinmd.cn\/col\/special\/image\/20171019\/1508381936597.jpg",
          "itemType": "1",
          "state": 0,
          "itemId": "1508381712911",
          "content": "热一个好人特殊用户人特殊用户人同时热一个好人特殊用户人特殊用户人同时热一个好人特殊用户人特殊用户人同时热一个好人特殊用户人特殊用户人同时热一个好人特殊用户人特殊用户人同时热一个好人特殊用户人特殊用户人同时热一个好人特殊用户人特殊用户人同时热一个好人特殊用户人特殊用户人同时热一个好人特殊用户人特殊用户人同时热一个好人特殊用户人特殊用户人同时热一个好人特殊用户人特殊用户人同时热一个好人特殊用户人特殊用户人同时热一个好人特殊用户人特殊用户人同时热一个好人特殊用户人特殊用户人同时热一个好人特殊用户人特殊用户人同时热一个好人特殊用户人特殊用户人同时热一个好人特殊用户人特殊用户人同时热一个好人特殊用户人特殊用户人同时热一个好人特殊用户人特殊用户人同时热一个好人特殊用户人特殊用户人同时热一个好人特殊用户人特殊用户人同时热一个好人特殊用户人特殊用户人同时热一个好人特殊用户人特殊用户人同时热一个好人特殊用户人特殊用户人同时热一个好人特殊用户人特殊用户人同时热一个好人特殊用户人特殊用户人同时热一个好人特殊用户人特殊用户人同时热一个好人特殊用户人特殊用户人同时热一个好人特殊用户人特殊用户人同时热一个好人特殊",
          "recommendTime": "1508745194933",
          "catalogNum": "",
          "browseNum": "",
          "isCollection": "",
          "itemGroup": "资源列",
          "recommendDate": "2017-10-23 15:53:14",
          "itemTitle": "资源列表排序",
          "itemUrl": ""
        },
        {
          "isFollow": "",
          "resourceNum": 27,
          "picUrl": "http:\/\/img04.allinmd.cn\/series\/attachment\/2017\/10\/11\/1507711784192.png",
          "itemType": "2",
          "state": 0,
          "itemId": "1502095181198",
          "content": "",
          "recommendTime": "1508742844691",
          "catalogNum": "12",
          "browseNum": "7134",
          "isCollection": "0",
          "itemGroup": "骨关节",
          "recommendDate": "2017-10-23 15:14:04",
          "itemTitle": "体系化课程-0807--0807（勿动）",
          "itemUrl": ""
        },
        {
          "isFollow": 0,
          "resourceNum": "",
          "picUrl": "https:\/\/img00.allinmd.cn\/col\/special\/image\/20171018\/1508303307632.jpg",
          "itemType": "1",
          "state": 0,
          "itemId": "1508226583367",
          "content": "特色栏目之骨科大讲堂公告：二级筛选的每个button内需显示该筛选项含有的资源数，每个tab下的多个二级筛选button在前台按资源数由多到少显示，无资源的筛选项前台不显示二级筛选的每个button内需显示该筛选项含有的资源数，每个tab下的多个二级筛选button在前台按资源数由多到少显示，无资源的筛选项前台不显示二级筛选的每个button内需显示该筛选项含有的资源数，每个tab下的多个二级筛选button在前台按资源数由多到少显示，无资源的筛选项前台不显示二级筛选的每个button内需显示该筛选项含有的资源数，每个tab下的多个二级筛选button在前台按资源数由多到少显示，无资源的筛选项前台不显示二级筛选的每个button内需显示该筛选项含有的资源数，每个tab下的多个二级筛选button在前台按资源数由多到少显示，无资源的筛选项前台不显示二级筛选的每个button内需显示该筛选项含有的资源数，每个tab下的多个二级筛选button在前台按资源数由多到少显示，无资源的筛选项前台不显示二级筛选的每个button内需显示该筛选项含有的资源数，每个tab下的多个二级筛选button在前",
          "recommendTime": "1508742115789",
          "catalogNum": "",
          "browseNum": "",
          "isCollection": "",
          "itemGroup": "",
          "recommendDate": "2017-10-23 15:01:55",
          "itemTitle": "勿动！特色栏目之骨科",
          "itemUrl": ""
        },
        {
          "isFollow": 0,
          "resourceNum": "",
          "picUrl": "https:\/\/img00.allinmd.cn\/col\/special\/image\/20171023\/1508739534803.jpg",
          "itemType": "1",
          "state": 0,
          "itemId": "1508739516072",
          "content": "SELECT* FROM  cms_special WHERE special_id=1508739516072SELECT* FROM  cms_special WHERE special_id=1508739516072SELECT* FROM  cms_special WHERE special_id=1508739516072SELECT* FROM  cms_special WHERE special_id=1508739516072",
          "recommendTime": "1508739587052",
          "catalogNum": "",
          "browseNum": "",
          "isCollection": "",
          "itemGroup": "梦奇",
          "recommendDate": "2017-10-23 14:19:47",
          "itemTitle": "梦奇v",
          "itemUrl": ""
        },
        {
          "isFollow": 0,
          "resourceNum": "",
          "picUrl": "https:\/\/img00.allinmd.cn\/col\/special\/image\/20171018\/1508291025031.jpg",
          "itemType": "1",
          "state": 0,
          "itemId": "1508290933444",
          "content": "这是公告内容，null这是公告内容,afgjiopdg；的光景萨姆vodd三管家婆我阿斯钢怕热的机关炮人很多的风格化噶尔热阿哈尔阿尔哈额噢噢噢噢噢噢噢噢哦哦噢噢噢噢噢噢噢噢哦哦哦哦哦哦哦哦哦哦哦哦哦哦哦哦哦哦哦哦哦fgfha",
          "recommendTime": "1508739281844",
          "catalogNum": "",
          "browseNum": "",
          "isCollection": "",
          "itemGroup": "",
          "recommendDate": "2017-10-23 14:14:41",
          "itemTitle": "",
          "itemUrl": ""
        },
        {
          "isFollow": 0,
          "resourceNum": "",
          "picUrl": "https:\/\/img00.allinmd.cn\/col\/special\/image\/20171018\/1508304456835.jpg",
          "itemType": "1",
          "state": 0,
          "itemId": "1508304250303",
          "content": "六十多个子六十多个子六十多个子六十多个子六十多个子六十多个子六十多",
          "recommendTime": "1508736737447",
          "catalogNum": "",
          "browseNum": "",
          "isCollection": "",
          "itemGroup": "特乐栏目副标题",
          "recommendDate": "2017-10-23 13:32:17",
          "itemTitle": "动勿-堂课英菁",
          "itemUrl": ""
        },
        {
          "isFollow": 0,
          "resourceNum": "",
          "picUrl": "https:\/\/img00.allinmd.cn\/col\/special\/image\/20171018\/1508293098360.jpg",
          "itemType": "1",
          "state": 0,
          "itemId": "1508292997574",
          "content": "01 时间之尺 我们应该怎样对待时间活在“全部的现在” 从当下出发，联结过去与未来 对五年后的自己提问 如何解决远期未来与近期未来的冲突？ 我们总是在重复地抓起沙子 把时间花在值得做的事情上 “快”与“慢”的自由切换 为什么我们的时间永远不够用？ \n",
          "recommendTime": "1508736735329",
          "catalogNum": "",
          "browseNum": "",
          "isCollection": "",
          "itemGroup": "时间之尺 我们应该怎样对待时间",
          "recommendDate": "2017-10-23 13:32:15",
          "itemTitle": "1018测试特色栏目xxx",
          "itemUrl": ""
        },
        {
          "isFollow": 0,
          "resourceNum": "",
          "picUrl": "https:\/\/img00.allinmd.cn\/col\/special\/image\/20171011\/1507689075806.jpg",
          "itemType": "1",
          "state": 0,
          "itemId": "1507688514000",
          "content": "甲乙丙丁戊甲乙丙丁戊甲乙丙丁戊甲乙丙丁戊甲乙丙丁戊甲乙丙丁戊甲乙丙丁戊甲乙丙丁戊甲乙丙丁戊甲乙丙丁戊甲乙丙丁戊甲乙丙丁戊甲乙丙丁戊甲乙丙丁戊甲乙丙丁戊甲乙丙丁戊甲乙丙丁戊",
          "recommendTime": "1508736733431",
          "catalogNum": "",
          "browseNum": "",
          "isCollection": "",
          "itemGroup": "一二三四五一二三四五一二三四五一二三四五",
          "recommendDate": "2017-10-23 13:32:13",
          "itemTitle": "一二三四五一二三四五",
          "itemUrl": ""
        },
        {
          "isFollow": 0,
          "resourceNum": "",
          "picUrl": "https:\/\/img00.allinmd.cn\/col\/special\/image\/20171017\/1508230502551.jpg",
          "itemType": "1",
          "state": 0,
          "itemId": "1508230474374",
          "content": "小王哥公告内容小王哥公告内容小王哥公告内容小王哥公告内容小王哥公告内容小王哥公告内容小王哥公告内容小王哥公告内容小王哥公告内容小王哥公告内容小王哥公告内容小王哥公告内容小王哥公告内容小王哥公告内容小王哥公告内容小王哥公告内容小王哥公告内容小王哥公告内容小王哥公告内容小王哥公告内容小王哥公告内容小王哥公告内容小王哥公告内容小王哥公告内容小王哥公告内容小王哥公告内容小王哥公告内容小王哥公告内容小王哥公告内容小王哥公告内容小王哥公告内容小王哥公告内容小王哥公告内容小王哥公告内容小王哥公告内容小王哥公告内容小王哥公告内容小王哥公告内容小王哥公告内容小王哥公告内容小王哥公告内容小王哥公告内容小王哥公告内容小王哥公告内容小王哥公告内容小王哥公告内容小王哥公告内容小王哥公告内容小王哥公告内容小王哥公告内容小王哥公告内容小王哥公告内容小王哥公告内容小王哥公告内容小王哥公告内容小王哥公告内容小王哥公告内容小王哥公告内容小王哥公告内容小王哥公告内容小王哥公告内容小王哥公告内容小王哥公告内容小王哥公告内容小王哥公告内容小王哥公告内容小王哥公告内容小王哥公告内容小王哥公告内容小王哥公告内容小王哥公告内容小王哥",
          "recommendTime": "1508736731777",
          "catalogNum": "",
          "browseNum": "",
          "isCollection": "",
          "itemGroup": "123",
          "recommendDate": "2017-10-23 13:32:11",
          "itemTitle": "小王哥骨科xxx",
          "itemUrl": ""
        },
        {
          "isFollow": 0,
          "resourceNum": "",
          "picUrl": "https:\/\/img00.allinmd.cn\/col\/special\/image\/20171020\/1508481826940.jpg",
          "itemType": "1",
          "state": 0,
          "itemId": "1508481320300",
          "content": "",
          "recommendTime": "1508736708875",
          "catalogNum": "",
          "browseNum": "",
          "isCollection": "",
          "itemGroup": "张元兴教授系列课程-髋关节置换术修复系列",
          "recommendDate": "2017-10-23 13:31:48",
          "itemTitle": " 精英课堂-张元兴",
          "itemUrl": ""
        }
      ],
      "total_count": 10
    },
    "responseCode": {},
    "responseStatus": true,
    "responsePk": 0
  }
}